setup.py
probability_dnsd/Binomialdistribution.py
probability_dnsd/Gaussiandistribution.py
probability_dnsd/Generaldistribution.py
probability_dnsd/__init__.py
probability_dnsd.egg-info/PKG-INFO
probability_dnsd.egg-info/SOURCES.txt
probability_dnsd.egg-info/dependency_links.txt
probability_dnsd.egg-info/not-zip-safe
probability_dnsd.egg-info/requires.txt
probability_dnsd.egg-info/top_level.txt