Metadata-Version: 1.0
Name: probability-dnsd
Version: 1
Summary: Gaussian and Binomial distributions
Home-page: UNKNOWN
Author: UNKNOWN
Author-email: arghyadeepsaha17@gmail.com
License: UNKNOWN
Platform: UNKNOWN
